kfsd/__init__.py
kfsd/asgi.py
kfsd/urls.py
kfsd/wsgi.py
kfsd/apps/__init__.py
kfsd/apps/frontend/__init__.py
kfsd/apps/frontend/apps.py
kfsd/apps/frontend/urls.py
kfsd/apps/models/__init__.py
kfsd/apps/models/apps.py
kfsd/apps/models/constants.py
kfsd/apps/models/models.py
kfsd/apps/models/signals.py
kfsd/apps/models/migrations/__init__.py
kfsd/settings/__init__.py
kfsd/settings/test.py
kfsd-0.0.218.dist-info/METADATA
kfsd-0.0.218.dist-info/WHEEL
kfsd-0.0.218.dist-info/top_level.txt
kfsd-0.0.218.dist-info/RECORD
