Metadata-Version: 2.1
Name: kfsd
Version: 0.0.218
Summary: Sample App
Home-page: UNKNOWN
Author: Gokul Nathan
Author-email: nathangokul111@gmail.com
License: UNKNOWN
Platform: UNKNOWN
